Classfile /Users/Barry/Professional/Workspaces/seed/javassist.samples/target/classes/net/madz/lifecycle/solutionOne/ServiceOrder.class
  Last modified 2013-10-21; size 3132 bytes
  MD5 checksum da427fcb9c46a8349fd5f07c3dce5d8a
  Compiled from "ServiceOrder.java"
public class net.madz.lifecycle.solutionOne.ServiceOrder implements net.madz.lifecycle.solutionOne.IServiceOrder
  SourceFile: "ServiceOrder.java"
  RuntimeVisibleAnnotations:
    0: #71(#46=c#72)
  InnerClasses:
       #10; //class net/madz/lifecycle/solutionOne/ServiceOrder$1
       public static #48= #47 of #87; //Transitions=class net/madz/lifecycle/demo/standalone/ServiceableLifecycleMeta$Transitions of class net/madz/lifecycle/demo/standalone/ServiceableLifecycleMeta
       public static #50= #49 of #47; //Schedule=class net/madz/lifecycle/demo/standalone/ServiceableLifecycleMeta$Transitions$Schedule of class net/madz/lifecycle/demo/standalone/ServiceableLifecycleMeta$Transitions
       public static #55= #54 of #47; //Start=class net/madz/lifecycle/demo/standalone/ServiceableLifecycleMeta$Transitions$Start of class net/madz/lifecycle/demo/standalone/ServiceableLifecycleMeta$Transitions
       public static #59= #58 of #47; //Finish=class net/madz/lifecycle/demo/standalone/ServiceableLifecycleMeta$Transitions$Finish of class net/madz/lifecycle/demo/standalone/ServiceableLifecycleMeta$Transitions
  minor version: 0
  major version: 51
  flags: ACC_PUBLIC, ACC_SUPER
Constant pool:
   #1 = Methodref          #20.#73        //  java/lang/Object."<init>":()V
   #2 = Class              #74            //  net/madz/lifecycle/solutionOne/InterceptorController
   #3 = Methodref          #2.#73         //  net/madz/lifecycle/solutionOne/InterceptorController."<init>":()V
   #4 = Class              #75            //  net/madz/lifecycle/solutionOne/InterceptContext
   #5 = Methodref          #20.#76        //  java/lang/Object.getClass:()Ljava/lang/Class;
   #6 = String             #31            //  allocateResources
   #7 = Class              #77            //  java/lang/Class
   #8 = Class              #78            //  java/lang/Long
   #9 = Methodref          #4.#79         //  net/madz/lifecycle/solutionOne/InterceptContext."<init>":(Ljava/lang/Class;Ljava/lang/Object;Ljava/lang/String;[Ljava/lang/Class;)V
  #10 = Class              #80            //  net/madz/lifecycle/solutionOne/ServiceOrder$1
  #11 = Methodref          #10.#81        //  net/madz/lifecycle/solutionOne/ServiceOrder$1."<init>":(Lnet/madz/lifecycle/solutionOne/ServiceOrder;JJJ)V
  #12 = Methodref          #2.#82         //  net/madz/lifecycle/solutionOne/InterceptorController.exec:(Lnet/madz/lifecycle/solutionOne/InterceptContext;Ljava/util/concurrent/Callable;)Ljava/lang/Object;
  #13 = Class              #83            //  net/madz/lifecycle/solutionOne/ServiceOrder
  #14 = Methodref          #13.#73        //  net/madz/lifecycle/solutionOne/ServiceOrder."<init>":()V
  #15 = Long               2l
  #17 = Long               3l
  #19 = Methodref          #13.#84        //  net/madz/lifecycle/solutionOne/ServiceOrder.allocateResources:(JJJ)V
  #20 = Class              #85            //  java/lang/Object
  #21 = Class              #86            //  net/madz/lifecycle/solutionOne/IServiceOrder
  #22 = Utf8               
  #23 = Utf8               InnerClasses
  #24 = Utf8               <init>
  #25 = Utf8               ()V
  #26 = Utf8               Code
  #27 = Utf8               LineNumberTable
  #28 = Utf8               LocalVariableTable
  #29 = Utf8               this
  #30 = Utf8               Lnet/madz/lifecycle/solutionOne/ServiceOrder;
  #31 = Utf8               allocateResources
  #32 = Utf8               (JJJ)V
  #33 = Utf8               summaryPlanId
  #34 = Utf8               J
  #35 = Utf8               truckResourceId
  #36 = Utf8               plangResourceId
  #37 = Utf8               controller
  #38 = Utf8               Lnet/madz/lifecycle/solutionOne/InterceptorController;
  #39 = Utf8               context
  #40 = Utf8               Lnet/madz/lifecycle/solutionOne/InterceptContext;
  #41 = Utf8               LocalVariableTypeTable
  #42 = Utf8               Lnet/madz/lifecycle/solutionOne/InterceptorController<Ljava/lang/Void;>;
  #43 = Utf8               Lnet/madz/lifecycle/solutionOne/InterceptContext<Ljava/lang/Void;>;
  #44 = Utf8               RuntimeVisibleAnnotations
  #45 = Utf8               Lnet/madz/lifecycle/annotations/Transition;
  #46 = Utf8               value
  #47 = Class              #88            //  net/madz/lifecycle/demo/standalone/ServiceableLifecycleMeta$Transitions
  #48 = Utf8               Transitions
  #49 = Class              #89            //  net/madz/lifecycle/demo/standalone/ServiceableLifecycleMeta$Transitions$Schedule
  #50 = Utf8               Schedule
  #51 = Utf8               Lnet/madz/lifecycle/demo/standalone/ServiceableLifecycleMeta$Transitions$Schedule;
  #52 = Utf8               allocateResources$Impl
  #53 = Utf8               confirmStart
  #54 = Class              #90            //  net/madz/lifecycle/demo/standalone/ServiceableLifecycleMeta$Transitions$Start
  #55 = Utf8               Start
  #56 = Utf8               Lnet/madz/lifecycle/demo/standalone/ServiceableLifecycleMeta$Transitions$Start;
  #57 = Utf8               confirmFinish
  #58 = Class              #91            //  net/madz/lifecycle/demo/standalone/ServiceableLifecycleMeta$Transitions$Finish
  #59 = Utf8               Finish
  #60 = Utf8               Lnet/madz/lifecycle/demo/standalone/ServiceableLifecycleMeta$Transitions$Finish;
  #61 = Utf8               getServiceOrderState
  #62 = Utf8               ()Ljava/lang/String;
  #63 = Utf8               Lnet/madz/lifecycle/annotations/StateIndicator;
  #64 = Utf8               main
  #65 = Utf8               ([Ljava/lang/String;)V
  #66 = Utf8               args
  #67 = Utf8               [Ljava/lang/String;
  #68 = Utf8               order
  #69 = Utf8               SourceFile
  #70 = Utf8               ServiceOrder.java
  #71 = Utf8               Lnet/madz/lifecycle/annotations/LifecycleMeta;
  #72 = Utf8               Lnet/madz/lifecycle/solutionOne/ServiceableLifecycleMeta;
  #73 = NameAndType        #24:#25        //  "<init>":()V
  #74 = Utf8               net/madz/lifecycle/solutionOne/InterceptorController
  #75 = Utf8               net/madz/lifecycle/solutionOne/InterceptContext
  #76 = NameAndType        #92:#93        //  getClass:()Ljava/lang/Class;
  #77 = Utf8               java/lang/Class
  #78 = Utf8               java/lang/Long
  #79 = NameAndType        #24:#94        //  "<init>":(Ljava/lang/Class;Ljava/lang/Object;Ljava/lang/String;[Ljava/lang/Class;)V
  #80 = Utf8               net/madz/lifecycle/solutionOne/ServiceOrder$1
  #81 = NameAndType        #24:#95        //  "<init>":(Lnet/madz/lifecycle/solutionOne/ServiceOrder;JJJ)V
  #82 = NameAndType        #96:#97        //  exec:(Lnet/madz/lifecycle/solutionOne/InterceptContext;Ljava/util/concurrent/Callable;)Ljava/lang/Object;
  #83 = Utf8               net/madz/lifecycle/solutionOne/ServiceOrder
  #84 = NameAndType        #31:#32        //  allocateResources:(JJJ)V
  #85 = Utf8               java/lang/Object
  #86 = Utf8               net/madz/lifecycle/solutionOne/IServiceOrder
  #87 = Class              #98            //  net/madz/lifecycle/demo/standalone/ServiceableLifecycleMeta
  #88 = Utf8               net/madz/lifecycle/demo/standalone/ServiceableLifecycleMeta$Transitions
  #89 = Utf8               net/madz/lifecycle/demo/standalone/ServiceableLifecycleMeta$Transitions$Schedule
  #90 = Utf8               net/madz/lifecycle/demo/standalone/ServiceableLifecycleMeta$Transitions$Start
  #91 = Utf8               net/madz/lifecycle/demo/standalone/ServiceableLifecycleMeta$Transitions$Finish
  #92 = Utf8               getClass
  #93 = Utf8               ()Ljava/lang/Class;
  #94 = Utf8               (Ljava/lang/Class;Ljava/lang/Object;Ljava/lang/String;[Ljava/lang/Class;)V
  #95 = Utf8               (Lnet/madz/lifecycle/solutionOne/ServiceOrder;JJJ)V
  #96 = Utf8               exec
  #97 = Utf8               (Lnet/madz/lifecycle/solutionOne/InterceptContext;Ljava/util/concurrent/Callable;)Ljava/lang/Object;
  #98 = Utf8               net/madz/lifecycle/demo/standalone/ServiceableLifecycleMeta
{
  public net.madz.lifecycle.solutionOne.ServiceOrder();
    Signature: ()V
    flags: ACC_PUBLIC
    LineNumberTable:
      line 13: 0
    LocalVariableTable:
      Start  Length  Slot  Name   Signature
             0       5     0  this   Lnet/madz/lifecycle/solutionOne/ServiceOrder;
    Code:
      stack=1, locals=1, args_size=1
         0: aload_0       
         1: invokespecial #1                  // Method java/lang/Object."<init>":()V
         4: return        
      LineNumberTable:
        line 13: 0
      LocalVariableTable:
        Start  Length  Slot  Name   Signature
               0       5     0  this   Lnet/madz/lifecycle/solutionOne/ServiceOrder;

  public void allocateResources(long, long, long);
    Signature: (JJJ)V
    flags: ACC_PUBLIC
    LineNumberTable:
      line 18: 0
      line 19: 9
      line 21: 47
      line 29: 67
    LocalVariableTable:
      Start  Length  Slot  Name   Signature
             0      68     0  this   Lnet/madz/lifecycle/solutionOne/ServiceOrder;
             0      68     1 summaryPlanId   J
             0      68     3 truckResourceId   J
             0      68     5 plangResourceId   J
             9      59     7 controller   Lnet/madz/lifecycle/solutionOne/InterceptorController;
            47      21     8 context   Lnet/madz/lifecycle/solutionOne/InterceptContext;
    Code:
      stack=11, locals=9, args_size=4
         0: new           #2                  // class net/madz/lifecycle/solutionOne/InterceptorController
         3: dup           
         4: invokespecial #3                  // Method net/madz/lifecycle/solutionOne/InterceptorController."<init>":()V
         7: astore        7
         9: new           #4                  // class net/madz/lifecycle/solutionOne/InterceptContext
        12: dup           
        13: aload_0       
        14: invokevirtual #5                  // Method java/lang/Object.getClass:()Ljava/lang/Class;
        17: aload_0       
        18: ldc           #6                  // String allocateResources
        20: iconst_3      
        21: anewarray     #7                  // class java/lang/Class
        24: dup           
        25: iconst_0      
        26: ldc_w         #8                  // class java/lang/Long
        29: aastore       
        30: dup           
        31: iconst_1      
        32: ldc_w         #8                  // class java/lang/Long
        35: aastore       
        36: dup           
        37: iconst_2      
        38: ldc_w         #8                  // class java/lang/Long
        41: aastore       
        42: invokespecial #9                  // Method net/madz/lifecycle/solutionOne/InterceptContext."<init>":(Ljava/lang/Class;Ljava/lang/Object;Ljava/lang/String;[Ljava/lang/Class;)V
        45: astore        8
        47: aload         7
        49: aload         8
        51: new           #10                 // class net/madz/lifecycle/solutionOne/ServiceOrder$1
        54: dup           
        55: aload_0       
        56: lload_1       
        57: lload_3       
        58: lload         5
        60: invokespecial #11                 // Method net/madz/lifecycle/solutionOne/ServiceOrder$1."<init>":(Lnet/madz/lifecycle/solutionOne/ServiceOrder;JJJ)V
        63: invokevirtual #12                 // Method net/madz/lifecycle/solutionOne/InterceptorController.exec:(Lnet/madz/lifecycle/solutionOne/InterceptContext;Ljava/util/concurrent/Callable;)Ljava/lang/Object;
        66: pop           
        67: return        
      LineNumberTable:
        line 18: 0
        line 19: 9
        line 21: 47
        line 29: 67
      LocalVariableTable:
        Start  Length  Slot  Name   Signature
               0      68     0  this   Lnet/madz/lifecycle/solutionOne/ServiceOrder;
               0      68     1 summaryPlanId   J
               0      68     3 truckResourceId   J
               0      68     5 plangResourceId   J
               9      59     7 controller   Lnet/madz/lifecycle/solutionOne/InterceptorController;
              47      21     8 context   Lnet/madz/lifecycle/solutionOne/InterceptContext;
      LocalVariableTypeTable:
        Start  Length  Slot  Name   Signature
            9      59     7 controller   Lnet/madz/lifecycle/solutionOne/InterceptorController<Ljava/lang/Void;>;
           47      21     8 context   Lnet/madz/lifecycle/solutionOne/InterceptContext<Ljava/lang/Void;>;
    RuntimeVisibleAnnotations:
      0: #45(#46=c#51)

  protected void allocateResources$Impl(long, long, long);
    Signature: (JJJ)V
    flags: ACC_PROTECTED
    LineNumberTable:
      line 33: 0
    LocalVariableTable:
      Start  Length  Slot  Name   Signature
             0       1     0  this   Lnet/madz/lifecycle/solutionOne/ServiceOrder;
             0       1     1 summaryPlanId   J
             0       1     3 truckResourceId   J
             0       1     5 plangResourceId   J
    Code:
      stack=0, locals=7, args_size=4
         0: return        
      LineNumberTable:
        line 33: 0
      LocalVariableTable:
        Start  Length  Slot  Name   Signature
               0       1     0  this   Lnet/madz/lifecycle/solutionOne/ServiceOrder;
               0       1     1 summaryPlanId   J
               0       1     3 truckResourceId   J
               0       1     5 plangResourceId   J

  public void confirmStart();
    Signature: ()V
    flags: ACC_PUBLIC
    LineNumberTable:
      line 38: 0
    LocalVariableTable:
      Start  Length  Slot  Name   Signature
             0       1     0  this   Lnet/madz/lifecycle/solutionOne/ServiceOrder;
    Code:
      stack=0, locals=1, args_size=1
         0: return        
      LineNumberTable:
        line 38: 0
      LocalVariableTable:
        Start  Length  Slot  Name   Signature
               0       1     0  this   Lnet/madz/lifecycle/solutionOne/ServiceOrder;
    RuntimeVisibleAnnotations:
      0: #45(#46=c#56)

  public void confirmFinish();
    Signature: ()V
    flags: ACC_PUBLIC
    LineNumberTable:
      line 43: 0
    LocalVariableTable:
      Start  Length  Slot  Name   Signature
             0       1     0  this   Lnet/madz/lifecycle/solutionOne/ServiceOrder;
    Code:
      stack=0, locals=1, args_size=1
         0: return        
      LineNumberTable:
        line 43: 0
      LocalVariableTable:
        Start  Length  Slot  Name   Signature
               0       1     0  this   Lnet/madz/lifecycle/solutionOne/ServiceOrder;
    RuntimeVisibleAnnotations:
      0: #45(#46=c#60)

  public java.lang.String getServiceOrderState();
    Signature: ()Ljava/lang/String;
    flags: ACC_PUBLIC
    LineNumberTable:
      line 48: 0
    LocalVariableTable:
      Start  Length  Slot  Name   Signature
             0       2     0  this   Lnet/madz/lifecycle/solutionOne/ServiceOrder;
    Code:
      stack=1, locals=1, args_size=1
         0: aconst_null   
         1: areturn       
      LineNumberTable:
        line 48: 0
      LocalVariableTable:
        Start  Length  Slot  Name   Signature
               0       2     0  this   Lnet/madz/lifecycle/solutionOne/ServiceOrder;
    RuntimeVisibleAnnotations:
      0: #63()

  public static void main(java.lang.String[]);
    Signature: ([Ljava/lang/String;)V
    flags: ACC_PUBLIC, ACC_STATIC
    LineNumberTable:
      line 52: 0
      line 53: 8
      line 54: 19
    LocalVariableTable:
      Start  Length  Slot  Name   Signature
             0      20     0  args   [Ljava/lang/String;
             8      12     1 order   Lnet/madz/lifecycle/solutionOne/ServiceOrder;
    Code:
      stack=7, locals=2, args_size=1
         0: new           #13                 // class net/madz/lifecycle/solutionOne/ServiceOrder
         3: dup           
         4: invokespecial #14                 // Method "<init>":()V
         7: astore_1      
         8: aload_1       
         9: lconst_1      
        10: ldc2_w        #15                 // long 2l
        13: ldc2_w        #17                 // long 3l
        16: invokevirtual #19                 // Method allocateResources:(JJJ)V
        19: return        
      LineNumberTable:
        line 52: 0
        line 53: 8
        line 54: 19
      LocalVariableTable:
        Start  Length  Slot  Name   Signature
               0      20     0  args   [Ljava/lang/String;
               8      12     1 order   Lnet/madz/lifecycle/solutionOne/ServiceOrder;
}
