Classfile /Users/Barry/Professional/Workspaces/seed/javassist.samples/target/classes/net/madz/lifecycle/demo/standalone/ServiceOrder.class
  Last modified 2013-10-23; size 2863 bytes
  MD5 checksum 0804a746fe784d193550209de8460cdb
  Compiled from "ServiceOrder.java"
public class net.madz.lifecycle.demo.standalone.ServiceOrder implements net.madz.lifecycle.demo.standalone.IServiceOrder
  SourceFile: "ServiceOrder.java"
  RuntimeVisibleAnnotations:
    0: #50(#30=c#51)
  InnerClasses:
       public static #32= #31 of #63; //Transitions=class net/madz/lifecycle/demo/standalone/ServiceableLifecycleMeta$Transitions of class net/madz/lifecycle/demo/standalone/ServiceableLifecycleMeta
       public static #35= #34 of #31; //Schedule=class net/madz/lifecycle/demo/standalone/ServiceableLifecycleMeta$Transitions$Schedule of class net/madz/lifecycle/demo/standalone/ServiceableLifecycleMeta$Transitions
       public static #39= #38 of #31; //Start=class net/madz/lifecycle/demo/standalone/ServiceableLifecycleMeta$Transitions$Start of class net/madz/lifecycle/demo/standalone/ServiceableLifecycleMeta$Transitions
       public static #43= #42 of #31; //Finish=class net/madz/lifecycle/demo/standalone/ServiceableLifecycleMeta$Transitions$Finish of class net/madz/lifecycle/demo/standalone/ServiceableLifecycleMeta$Transitions
       #94 of #7; //class net/madz/lifecycle/demo/standalone/ServiceOrder$5 of class net/madz/lifecycle/demo/standalone/ServiceOrder
  minor version: 0
  major version: 50
  flags: ACC_PUBLIC, ACC_SUPER
Constant pool:
    #1 = Methodref          #8.#52        //  java/lang/Object."<init>":()V
    #2 = Fieldref           #53.#54       //  java/lang/System.out:Ljava/io/PrintStream;
    #3 = String             #55           //  confirmStart ...
    #4 = Methodref          #56.#57       //  java/io/PrintStream.println:(Ljava/lang/String;)V
    #5 = String             #58           //  confirmFinish ...
    #6 = Fieldref           #7.#59        //  net/madz/lifecycle/demo/standalone/ServiceOrder.state:Ljava/lang/String;
    #7 = Class              #60           //  net/madz/lifecycle/demo/standalone/ServiceOrder
    #8 = Class              #61           //  java/lang/Object
    #9 = Class              #62           //  net/madz/lifecycle/demo/standalone/IServiceOrder
   #10 = Utf8               state
   #11 = Utf8               Ljava/lang/String;
   #12 = Utf8               <init>
   #13 = Utf8               ()V
   #14 = Utf8               Code
   #15 = Utf8               LineNumberTable
   #16 = Utf8               LocalVariableTable
   #17 = Utf8               this
   #18 = Utf8               Lnet/madz/lifecycle/demo/standalone/ServiceOrder;
   #19 = Utf8               allocateResources
   #20 = Utf8               (JJJ)V
   #21 = Utf8               summaryPlanId
   #22 = Utf8               J
   #23 = Utf8               truckResourceId
   #24 = Utf8               plangResourceId
   #25 = Utf8               x
   #26 = Utf8               y
   #27 = Utf8               z
   #28 = Utf8               RuntimeVisibleAnnotations
   #29 = Utf8               Lnet/madz/lifecycle/annotations/Transition;
   #30 = Utf8               value
   #31 = Class              #64           //  net/madz/lifecycle/demo/standalone/ServiceableLifecycleMeta$Transitions
   #32 = Utf8               Transitions
   #33 = Utf8               InnerClasses
   #34 = Class              #65           //  net/madz/lifecycle/demo/standalone/ServiceableLifecycleMeta$Transitions$Schedule
   #35 = Utf8               Schedule
   #36 = Utf8               Lnet/madz/lifecycle/demo/standalone/ServiceableLifecycleMeta$Transitions$Schedule;
   #37 = Utf8               confirmStart
   #38 = Class              #66           //  net/madz/lifecycle/demo/standalone/ServiceableLifecycleMeta$Transitions$Start
   #39 = Utf8               Start
   #40 = Utf8               Lnet/madz/lifecycle/demo/standalone/ServiceableLifecycleMeta$Transitions$Start;
   #41 = Utf8               confirmFinish
   #42 = Class              #67           //  net/madz/lifecycle/demo/standalone/ServiceableLifecycleMeta$Transitions$Finish
   #43 = Utf8               Finish
   #44 = Utf8               Lnet/madz/lifecycle/demo/standalone/ServiceableLifecycleMeta$Transitions$Finish;
   #45 = Utf8               getServiceOrderState
   #46 = Utf8               ()Ljava/lang/String;
   #47 = Utf8               Lnet/madz/lifecycle/annotations/StateIndicator;
   #48 = Utf8               SourceFile
   #49 = Utf8               ServiceOrder.java
   #50 = Utf8               Lnet/madz/lifecycle/annotations/LifecycleMeta;
   #51 = Utf8               Lnet/madz/lifecycle/demo/standalone/ServiceableLifecycleMeta;
   #52 = NameAndType        #12:#13       //  "<init>":()V
   #53 = Class              #68           //  java/lang/System
   #54 = NameAndType        #69:#70       //  out:Ljava/io/PrintStream;
   #55 = Utf8               confirmStart ...
   #56 = Class              #71           //  java/io/PrintStream
   #57 = NameAndType        #72:#73       //  println:(Ljava/lang/String;)V
   #58 = Utf8               confirmFinish ...
   #59 = NameAndType        #10:#11       //  state:Ljava/lang/String;
   #60 = Utf8               net/madz/lifecycle/demo/standalone/ServiceOrder
   #61 = Utf8               java/lang/Object
   #62 = Utf8               net/madz/lifecycle/demo/standalone/IServiceOrder
   #63 = Class              #74           //  net/madz/lifecycle/demo/standalone/ServiceableLifecycleMeta
   #64 = Utf8               net/madz/lifecycle/demo/standalone/ServiceableLifecycleMeta$Transitions
   #65 = Utf8               net/madz/lifecycle/demo/standalone/ServiceableLifecycleMeta$Transitions$Schedule
   #66 = Utf8               net/madz/lifecycle/demo/standalone/ServiceableLifecycleMeta$Transitions$Start
   #67 = Utf8               net/madz/lifecycle/demo/standalone/ServiceableLifecycleMeta$Transitions$Finish
   #68 = Utf8               java/lang/System
   #69 = Utf8               out
   #70 = Utf8               Ljava/io/PrintStream;
   #71 = Utf8               java/io/PrintStream
   #72 = Utf8               println
   #73 = Utf8               (Ljava/lang/String;)V
   #74 = Utf8               net/madz/lifecycle/demo/standalone/ServiceableLifecycleMeta
   #75 = Utf8               allocateResources$Impl
   #76 = Utf8               net/madz/lifecycle/solutionOne/InterceptorController
   #77 = Class              #76           //  net/madz/lifecycle/solutionOne/InterceptorController
   #78 = Methodref          #77.#52       //  net/madz/lifecycle/solutionOne/InterceptorController."<init>":()V
   #79 = Utf8               net/madz/lifecycle/solutionOne/InterceptContext
   #80 = Class              #79           //  net/madz/lifecycle/solutionOne/InterceptContext
   #81 = Utf8               getClass
   #82 = Utf8               ()Ljava/lang/Class;
   #83 = NameAndType        #81:#82       //  getClass:()Ljava/lang/Class;
   #84 = Methodref          #7.#83        //  net/madz/lifecycle/demo/standalone/ServiceOrder.getClass:()Ljava/lang/Class;
   #85 = String             #19           //  allocateResources
   #86 = Utf8               java/lang/Class
   #87 = Class              #86           //  java/lang/Class
   #88 = Utf8               java/lang/Long
   #89 = Class              #88           //  java/lang/Long
   #90 = Utf8               (Ljava/lang/Class;Ljava/lang/Object;Ljava/lang/String;[Ljava/lang/Class;)V
   #91 = NameAndType        #12:#90       //  "<init>":(Ljava/lang/Class;Ljava/lang/Object;Ljava/lang/String;[Ljava/lang/Class;)V
   #92 = Methodref          #80.#91       //  net/madz/lifecycle/solutionOne/InterceptContext."<init>":(Ljava/lang/Class;Ljava/lang/Object;Ljava/lang/String;[Ljava/lang/Class;)V
   #93 = Utf8               net/madz/lifecycle/demo/standalone/ServiceOrder$5
   #94 = Class              #93           //  net/madz/lifecycle/demo/standalone/ServiceOrder$5
   #95 = Utf8               (Lnet/madz/lifecycle/demo/standalone/ServiceOrder;JJJ)V
   #96 = NameAndType        #12:#95       //  "<init>":(Lnet/madz/lifecycle/demo/standalone/ServiceOrder;JJJ)V
   #97 = Methodref          #94.#96       //  net/madz/lifecycle/demo/standalone/ServiceOrder$5."<init>":(Lnet/madz/lifecycle/demo/standalone/ServiceOrder;JJJ)V
   #98 = Utf8               exec
   #99 = Utf8               (Lnet/madz/lifecycle/solutionOne/InterceptContext;Ljava/util/concurrent/Callable;)Ljava/lang/Object;
  #100 = NameAndType        #98:#99       //  exec:(Lnet/madz/lifecycle/solutionOne/InterceptContext;Ljava/util/concurrent/Callable;)Ljava/lang/Object;
  #101 = Methodref          #77.#100      //  net/madz/lifecycle/solutionOne/InterceptorController.exec:(Lnet/madz/lifecycle/solutionOne/InterceptContext;Ljava/util/concurrent/Callable;)Ljava/lang/Object;
{
  private java.lang.String state;
    Signature: Ljava/lang/String;
    flags: ACC_PRIVATE


  public net.madz.lifecycle.demo.standalone.ServiceOrder();
    Signature: ()V
    flags: ACC_PUBLIC
    LineNumberTable:
      line 11: 0
    LocalVariableTable:
      Start  Length  Slot  Name   Signature
             0       5     0  this   Lnet/madz/lifecycle/demo/standalone/ServiceOrder;
    Code:
      stack=1, locals=1, args_size=1
         0: aload_0       
         1: invokespecial #1                  // Method java/lang/Object."<init>":()V
         4: return        
      LineNumberTable:
        line 11: 0
      LocalVariableTable:
        Start  Length  Slot  Name   Signature
               0       5     0  this   Lnet/madz/lifecycle/demo/standalone/ServiceOrder;
 
  public void allocateResources(long, long, long);
    Signature: (JJJ)V
    flags: ACC_PUBLIC
    RuntimeVisibleAnnotations:
      0: #29(#30=c#36)
    Code:
      stack=11, locals=9, args_size=4
         0: new           #77                 // class net/madz/lifecycle/solutionOne/InterceptorController
         3: dup           
         4: invokespecial #78                 // Method net/madz/lifecycle/solutionOne/InterceptorController."<init>":()V
         7: astore        7
         9: new           #80                 // class net/madz/lifecycle/solutionOne/InterceptContext
        12: dup           
        13: aload_0       
        14: invokevirtual #84                 // Method getClass:()Ljava/lang/Class;
        17: aload_0       
        18: ldc           #85                 // String allocateResources
        20: iconst_3      
        21: anewarray     #87                 // class java/lang/Class
        24: dup           
        25: iconst_0      
        26: ldc           #89                 // class java/lang/Long
        28: aastore       
        29: dup           
        30: iconst_1      
        31: ldc           #89                 // class java/lang/Long
        33: aastore       
        34: dup           
        35: iconst_2      
        36: ldc           #89                 // class java/lang/Long
        38: aastore       
        39: invokespecial #92                 // Method net/madz/lifecycle/solutionOne/InterceptContext."<init>":(Ljava/lang/Class;Ljava/lang/Object;Ljava/lang/String;[Ljava/lang/Class;)V
        42: astore        8
        44: aload         7
        46: aload         8
        48: new           #94                 // class net/madz/lifecycle/demo/standalone/ServiceOrder$5
        51: dup           
        52: aload_0       
        53: lload_1       
        54: lload_3       
        55: lload         5
        57: invokespecial #97                 // Method net/madz/lifecycle/demo/standalone/ServiceOrder$5."<init>":(Lnet/madz/lifecycle/demo/standalone/ServiceOrder;JJJ)V
        60: invokespecial #101                // Method net/madz/lifecycle/solutionOne/InterceptorController.exec:(Lnet/madz/lifecycle/solutionOne/InterceptContext;Ljava/util/concurrent/Callable;)Ljava/lang/Object;
        63: pop           
        64: return        

  public void confirmStart();
    Signature: ()V
    flags: ACC_PUBLIC
    LineNumberTable:
      line 26: 0
      line 27: 8
    LocalVariableTable:
      Start  Length  Slot  Name   Signature
             0       9     0  this   Lnet/madz/lifecycle/demo/standalone/ServiceOrder;
    Code:
      stack=2, locals=1, args_size=1
         0: getstatic     #2                  // Field java/lang/System.out:Ljava/io/PrintStream;
         3: ldc           #3                  // String confirmStart ...
         5: invokevirtual #4                  // Method java/io/PrintStream.println:(Ljava/lang/String;)V
         8: return        
      LineNumberTable:
        line 26: 0
        line 27: 8
      LocalVariableTable:
        Start  Length  Slot  Name   Signature
               0       9     0  this   Lnet/madz/lifecycle/demo/standalone/ServiceOrder;
    RuntimeVisibleAnnotations:
      0: #29(#30=c#40)

  public void confirmFinish();
    Signature: ()V
    flags: ACC_PUBLIC
    LineNumberTable:
      line 32: 0
      line 33: 8
    LocalVariableTable:
      Start  Length  Slot  Name   Signature
             0       9     0  this   Lnet/madz/lifecycle/demo/standalone/ServiceOrder;
    Code:
      stack=2, locals=1, args_size=1
         0: getstatic     #2                  // Field java/lang/System.out:Ljava/io/PrintStream;
         3: ldc           #5                  // String confirmFinish ...
         5: invokevirtual #4                  // Method java/io/PrintStream.println:(Ljava/lang/String;)V
         8: return        
      LineNumberTable:
        line 32: 0
        line 33: 8
      LocalVariableTable:
        Start  Length  Slot  Name   Signature
               0       9     0  this   Lnet/madz/lifecycle/demo/standalone/ServiceOrder;
    RuntimeVisibleAnnotations:
      0: #29(#30=c#44)

  public java.lang.String getServiceOrderState();
    Signature: ()Ljava/lang/String;
    flags: ACC_PUBLIC
    LineNumberTable:
      line 38: 0
    LocalVariableTable:
      Start  Length  Slot  Name   Signature
             0       5     0  this   Lnet/madz/lifecycle/demo/standalone/ServiceOrder;
    Code:
      stack=1, locals=1, args_size=1
         0: aload_0       
         1: getfield      #6                  // Field state:Ljava/lang/String;
         4: areturn       
      LineNumberTable:
        line 38: 0
      LocalVariableTable:
        Start  Length  Slot  Name   Signature
               0       5     0  this   Lnet/madz/lifecycle/demo/standalone/ServiceOrder;
    RuntimeVisibleAnnotations:
      0: #47()

  public void allocateResources$Impl(long, long, long);
    Signature: (JJJ)V
    flags: ACC_PUBLIC
    LineNumberTable:
      line 18: 0
      line 19: 3
      line 20: 7
      line 21: 10
    LocalVariableTable:
      Start  Length  Slot  Name   Signature
             0      11     0  this   Lnet/madz/lifecycle/demo/standalone/ServiceOrder;
             0      11     1 summaryPlanId   J
             0      11     3 truckResourceId   J
             0      11     5 plangResourceId   J
             3       8     7     x   J
             7       4     9     y   J
            10       0    11     z   J
    RuntimeVisibleAnnotations:
      0: #29(#30=c#36)
    Code:
      stack=2, locals=13, args_size=4
         0: lconst_0      
         1: lstore        7
         3: lload         7
         5: lstore        9
         7: lconst_0      
         8: lstore        11
        10: return        
      LocalVariableTable:
        Start  Length  Slot  Name   Signature
               0      11     0  this   Lnet/madz/lifecycle/demo/standalone/ServiceOrder;
               0      11     1 summaryPlanId   J
               0      11     3 truckResourceId   J
               0      11     5 plangResourceId   J
               3       8     7     x   J
               7       4     9     y   J
              10       0    11     z   J
      LineNumberTable:
        line 18: 0
        line 19: 3
        line 20: 7
        line 21: 10

}
